Register_Unit.sv
module Register_Unit (
    input logic RUWr,
    input logic clk,
    input logic [4:0] rs1,
    input logic [4:0] rs2,
    input logic [4:0] rd,
    input logic [31:0] RUDataWr,
    output logic [31:0] RUrs1,
    output logic [31:0] RUrs2
);

    logic [31:0] RU32 [0:31];

	initial
    begin
        for (int i = 0; i < 32; i++) begin
            RU32[i] = 32'b0;
        end
        RU32[2] = 32'd1000;
    end

    always @(posedge clk)
    begin
        if(RUWr && (rd!=0))
        begin
            RU32[rd] <= RUDataWr;
        end
    end

    assign RUrs1 = RU32[rs1];
    assign RUrs2 = RU32[rs2];
    
endmodule

PC.sv
module PC (
    input logic clk,
    input logic [31:0] PC_Input,
    output logic [31:0] PC_Output
);

    initial 
    begin
        PC_Output = 32'b0;
    end
    
    always @(posedge clk)
    begin
        PC_Output = PC_Input;
    end

endmodule

Instruction_Memory.sv
module Instruction_Memory(
  input logic [31:0]address,
  output logic [31:0]instruction
);

  logic [7:0] BIOS [0:255];
  
  initial begin
    $readmemh("test_2.txt", BIOS);
  end

  assign instruction = {BIOS[address], BIOS[address+1], BIOS[address+2], BIOS[address+3]};
  
endmodule

Imm_Gen.sv
module Imm_Gen (
    input logic [24:0] Inst,
    input logic [2:0] ImmSrc,
    output logic [31:0] ImmExt
);

    always @(*)
    begin
        case (ImmSrc)
            3'b000 : ImmExt = (Inst[7:5]==3'b101 || Inst[7:5]==3'b001) ? {{27{Inst[17]}}, Inst[17:13]}: {{20{Inst[24]}}, Inst[24:13]}; //Tipo I
            3'b001 : ImmExt = {{20{Inst[24]}}, Inst[24:18], Inst[4:0]}; //Tipo S
            3'b101 : ImmExt = {{19{Inst[24]}}, Inst[24], Inst[0], Inst[23:18], Inst[4:1], 1'b0}; //Tipo B
            3'b010 : ImmExt = {Inst[24:5], 12'b0}; //Tipo U
            3'b110 : ImmExt = {{11{Inst[24]}}, Inst[24], Inst[12:5], Inst[13], Inst[23:14], 1'b0}; //Tipo J
            default: ImmExt = 32'b0;
        endcase        
    end
    
endmodule

Data_Memory.sv
module Data_Memory (
    input logic [31:0] Address,
    input logic [31:0] DataWr,
    input logic DMWr,
    input logic [2:0] DMCtrl,
    output logic [31:0] DataRd
);
    
    logic [7:0] data_mem [0:2048];

    initial
    begin
        for (int i = 0; i < 2048; i++) begin
            data_mem[i] = 8'b0;
        end
    end

    always @(*)
    begin
        if(DMWr)
        begin
            #1
            case (DMCtrl)
                3'b000, 3'b100:
                begin
                    data_mem[Address+3] <= DataWr[7:0];
                end
                3'b001, 3'b101:
                begin
                    data_mem[Address+2] <= DataWr[15:8];
                    data_mem[Address+3] <= DataWr[7:0];
                end
                3'b010:
                begin
                    data_mem[Address] <= DataWr[31:24];
                    data_mem[Address+1] <= DataWr[23:16];
                    data_mem[Address+2] <= DataWr[15:8];
                    data_mem[Address+3] <= DataWr[7:0];
                end
            endcase
        end

        case (DMCtrl)
            3'b000: DataRd = {{{24{data_mem[Address+3][7]}}}, data_mem[Address+3]};
            3'b001: DataRd = {{{16{data_mem[Address+2][7]}}}, data_mem[Address+2], data_mem[Address+3]};  
            3'b010: DataRd = {data_mem[Address], data_mem[Address+1], data_mem[Address+2], data_mem[Address+3]};  
            3'b100: DataRd = {24'b0, data_mem[Address+3]};  
            3'b101: DataRd = {16'b0, data_mem[Address+2], data_mem[Address+3]};    
        endcase
    end
endmodule

Control_Unit.sv
module Control_Unit (
    input logic [6:0] OpCode,
    input logic [2:0] Funct3,
    input logic [6:0] Funct7,
    output logic ALUASrc,
    output logic ALUBSrc,
    output logic [3:0] ALUOp,
    output logic [4:0] BrOp,
    output logic DMWr,
    output logic [2:0] DMCtrl,
    output logic RUWr,
    output logic [1:0] RUDATAWrSrc,
    output logic [2:0] ImmSrc
);
    always @(*) begin
        case (OpCode)
        7'b0110011: //Tipo R
        begin
            ALUASrc = 1'b0;
            ALUBSrc = 1'b0;
            ALUOp = {Funct7[5], Funct3};
            BrOp = 5'b0;
            DMWr = 1'b0;
            DMCtrl = 3'b0;
            RUWr = 1'b1;
            RUDATAWrSrc = 2'b0;
            ImmSrc =3'b0;
        end
        7'b0010011: //Tipo I
        begin
            ALUASrc = 1'b0;
            ALUBSrc = 1'b1;
            if (Funct3 == 3'b101 || Funct3 == 3'b001) begin
                ALUOp = {Funct7[5], Funct3};
            end else begin
                ALUOp = {1'b0, Funct3};
            end
            BrOp = 5'b0;
            DMWr = 1'b0;
            DMCtrl = 3'b0;
            RUWr = 1'b1;
            RUDATAWrSrc = 2'b0;
            ImmSrc =3'b0;
        end
        7'b0000011: //Tipo I-Lectura
        begin
            ALUASrc = 1'b0;
            ALUBSrc = 1'b1;
            ALUOp = 4'b0;
            BrOp = 5'b0;
            DMWr = 1'b0;
            DMCtrl = Funct3;
            RUWr = 1'b1;
            RUDATAWrSrc = 2'b01;
            ImmSrc =3'b0;
        end
        7'b1100111: //Tipo I-Salto
        begin
            ALUASrc = 1'b0;
            ALUBSrc = 1'b1;
            ALUOp = 4'b0;
            BrOp = 5'b10000;
            DMWr = 1'b0;
            DMCtrl = 3'b0;
            RUWr = 1'b1;
            RUDATAWrSrc = 2'b10;
            ImmSrc =3'b0;
        end
        7'b0100011: //Tipo S
        begin
            ALUASrc = 1'b0;
            ALUBSrc = 1'b1;
            ALUOp = 4'b0;
            BrOp = 5'b0;
            DMWr = 1'b1;
            DMCtrl = Funct3;
            RUWr = 1'b0;
            RUDATAWrSrc = 2'b10;
            ImmSrc =3'b001;
        end
        7'b1100011: //Tipo B
        begin
            ALUASrc = 1'b1;
            ALUBSrc = 1'b1;
            ALUOp = 4'b0;
            BrOp = {2'b01, Funct3};
            DMWr = 1'b0;
            DMCtrl = 3'b0;
            RUWr = 1'b0;
            RUDATAWrSrc = 2'b10;
            ImmSrc =3'b101;
        end
        7'b1101111: //Tipo J
        begin
            ALUASrc = 1'b1;
            ALUBSrc = 1'b1;
            ALUOp = 4'b0;
            BrOp = 5'b10000;
            DMWr = 1'b0;
            DMCtrl = 3'b0;
            RUWr = 1'b1;
            RUDATAWrSrc = 2'b10;
            ImmSrc =3'b110;
        end
        7'b0110111: //Tipo U-lui
        begin
            ALUASrc = 1'b0;
            ALUBSrc = 1'b1;
            ALUOp = 4'b0111;
            BrOp = 5'b0;
            DMWr = 1'b0;
            DMCtrl = 3'b0;
            RUWr = 1'b0;
            RUDATAWrSrc = 2'b0;
            ImmSrc =3'b010;
        end
        7'b0010111: //Tipo U-auipc
        begin
            ALUASrc = 1'b1;
            ALUBSrc = 1'b1;
            ALUOp = 4'b0000;
            BrOp = 5'b0;
            DMWr = 1'b0;
            DMCtrl = 3'b0;
            RUWr = 1'b1;
            RUDATAWrSrc = 2'b0;
            ImmSrc =3'b010;
        end
    endcase
    end
endmodule

Branch_Unit.sv
module Branch_Unit (
    input logic signed [31:0] BRUrs1,
    input logic signed [31:0] BRUrs2,
    input logic [4:0] BrOp,
    output logic NextPCSrc
);

    always @(*)
    begin
        if (BrOp[4]==1) begin
            NextPCSrc <= 1;
        end else if (BrOp[4:3]==2'b00) begin
            NextPCSrc <= 0;
        end else if(BrOp[4:3]==2'b01) begin
            if (BrOp[2:0]==3'b000) begin
                NextPCSrc <= (BRUrs1==BRUrs2);
            end else if (BrOp[2:0]==3'b001) begin
                NextPCSrc <= (BRUrs1!=BRUrs2);
            end else if (BrOp[2:0]==3'b100) begin
                NextPCSrc <= (BRUrs1<BRUrs2);
            end else if (BrOp[2:0]==3'b101) begin
                NextPCSrc <= (BRUrs1>=BRUrs2);
            end else if (BrOp[2:0]==3'b101) begin
                NextPCSrc <= (BRUrs1>=BRUrs2);
            end else if (BrOp[2:0]==3'b110) begin
                NextPCSrc <= ($unsigned(BRUrs1)<$unsigned(BRUrs2));
            end else if (BrOp[2:0]==3'b111) begin
                NextPCSrc <= ($unsigned(BRUrs1)>=$unsigned(BRUrs2));
            end
        end
    end
    
endmodule

ALU.sv
module ALU(
  input logic signed [31:0] A, 
  input logic signed [31:0] B,
  input logic [3:0] Op,
  output logic signed [31:0] ALURes
);
  
  always_comb begin
    case(Op)
      4'b0000 : ALURes = A+B;
      4'b1000 : ALURes = A-B;
      4'b0001 : ALURes = A<<B;
      4'b0010 : ALURes = A<B;
      4'b0011 : ALURes = $unsigned(A)<$unsigned(B);
      4'b0100 : ALURes = A^B;
      4'b0101 : ALURes = A>>B;
      4'b1101 : ALURes = A>>>B;
      4'b0110 : ALURes = A|B;
      4'b0111 : ALURes = A&B;
      default : ALURes = 0;
    endcase
  end
endmodule

Unicycle_Design.sv
`include "ALU.sv"
`include "Branch_Unit.sv"
`include "Control_Unit.sv"
`include "Data_Memory.sv"
`include "Imm_Gen.sv"
`include "Instruction_Memory.sv"
`include "PC.sv"
`include "Register_Unit.sv"

module Unicycle_Design (
    input logic clk,
    output logic [31:0] result //Sólo sirve para el Testbench
);
    //ALU
    logic signed [31:0] A; 
    logic signed [31:0] B;
    logic signed [31:0] ALURes;

    //Branch_Unit
    logic NextPCSrc;

    //Control_Unit
    logic ALUASrc;
    logic ALUBSrc;
    logic [3:0] ALUOp;
    logic [4:0] BrOp;
    logic DMWr;
    logic [2:0] DMCtrl;
    logic RUWr;
    logic [1:0] RUDATAWrSrc;
    logic [2:0] ImmSrc;

    //Data_Memory
    logic [31:0] DataRd;

    //Imm_Gen
    logic [31:0] ImmExt;

    //Instruction_Memory
    logic [31:0] instruction;

    //Sumador
    logic [31:0] sumador;
    
    //PC
    logic [31:0] PC_Input;
    logic [31:0] PC_Output;

    //Register_Unit
    logic [31:0] RUrs1;
    logic [31:0] RUrs2;

    always @(*) begin
        sumador = PC_Output + 4;

        PC_Input <= NextPCSrc ? ALURes : sumador;
        A <= ALUASrc ? PC_Output : RUrs1;
        B <= ALUBSrc ? ImmExt : RUrs2;
    end


    ALU alu(
        .A(A), 
        .B(B),
        .Op(ALUOp),
        .ALURes(ALURes)
    );

    Branch_Unit branch_unit(
        .BRUrs1(RUrs1),
        .BRUrs2(RUrs2),
        .BrOp(BrOp),
        .NextPCSrc(NextPCSrc)
    );

    Control_Unit control_unit(
        .OpCode(instruction[6:0]),
        .Funct3(instruction[14:12]),
        .Funct7(instruction[31:25]),
        .ALUASrc(ALUASrc),
        .ALUBSrc(ALUBSrc),
        .ALUOp(ALUOp),
        .BrOp(BrOp),
        .DMWr(DMWr),
        .DMCtrl(DMCtrl),
        .RUWr(RUWr),
        .RUDATAWrSrc(RUDATAWrSrc),
        .ImmSrc(ImmSrc)
    );

    Data_Memory data_memory(
        .Address(ALURes),
        .DataWr(RUrs2),
        .DMWr(DMWr),
        .DMCtrl(DMCtrl),
        .DataRd(DataRd)
    );

    Imm_Gen imm_gen(
        .Inst(instruction[31:7]),
        .ImmSrc(ImmSrc),
        .ImmExt(ImmExt)
    );

    Instruction_Memory instruction_memory(
        .address(PC_Output),
        .instruction(instruction)
    );

    PC programm_counter(
        .clk(clk),
        .PC_Input(PC_Input),
        .PC_Output(PC_Output)
    );

    Register_Unit register_unit(
        .RUWr(RUWr),
        .clk(clk),
        .rs1(instruction[19:15]),
        .rs2(instruction[24:20]),
        .rd(instruction[11:7]),
        .RUDataWr((RUDATAWrSrc==2'b00) ? ALURes: ((RUDATAWrSrc==2'b01) ? DataRd: ((RUDATAWrSrc==2'b10) ? sumador: 2'b00))),
        .RUrs1(RUrs1),
        .RUrs2(RUrs2)
    );

    assign result = ALURes;


endmodule

Testbench_Unicycle_Design.sv
module tb_Unicycle_Design;
    logic clk;
    logic [31:0] result;

    Unicycle_Design Unicycle_Design_Test(
        .clk(clk),
        .result(result)
    );
    
    always
    begin
        #5 clk = ~clk;
    end

    initial begin
        $dumpfile("dump.vcd");
        $dumpvars;

        $monitor("Result = %h", result);

        clk = 0;

        #100000;
        $finish;
    end
endmodule

dump.vcd
$date
	Thu May 09 21:18:10 2024
$end
$version
	Icarus Verilog
$end
$timescale
	1s
$end
$scope module tb_Unicycle_Design $end
$var wire 32 ! result [31:0] $end
$var reg 1 " clk $end
$scope module Unicycle_Design_Test $end
$var wire 1 " clk $end
$var wire 32 # result [31:0] $end
$var wire 32 $ instruction [31:0] $end
$var wire 32 % RUrs2 [31:0] $end
$var wire 32 & RUrs1 [31:0] $end
$var wire 1 ' RUWr $end
$var wire 2 ( RUDATAWrSrc [1:0] $end
$var wire 32 ) PC_Output [31:0] $end
$var wire 1 * NextPCSrc $end
$var wire 3 + ImmSrc [2:0] $end
$var wire 32 , ImmExt [31:0] $end
$var wire 32 - DataRd [31:0] $end
$var wire 1 . DMWr $end
$var wire 3 / DMCtrl [2:0] $end
$var wire 5 0 BrOp [4:0] $end
$var wire 32 1 ALURes [31:0] $end
$var wire 4 2 ALUOp [3:0] $end
$var wire 1 3 ALUBSrc $end
$var wire 1 4 ALUASrc $end
$var reg 32 5 A [31:0] $end
$var reg 32 6 B [31:0] $end
$var reg 32 7 PC_Input [31:0] $end
$var reg 32 8 sumador [31:0] $end
$scope module alu $end
$var wire 32 9 A [31:0] $end
$var wire 32 : B [31:0] $end
$var wire 4 ; Op [3:0] $end
$var reg 32 < ALURes [31:0] $end
$upscope $end
$scope module branch_unit $end
$var wire 5 = BrOp [4:0] $end
$var wire 32 > BRUrs2 [31:0] $end
$var wire 32 ? BRUrs1 [31:0] $end
$var reg 1 * NextPCSrc $end
$upscope $end
$scope module control_unit $end
$var wire 3 @ Funct3 [2:0] $end
$var wire 7 A Funct7 [6:0] $end
$var wire 7 B OpCode [6:0] $end
$var reg 1 4 ALUASrc $end
$var reg 1 3 ALUBSrc $end
$var reg 4 C ALUOp [3:0] $end
$var reg 5 D BrOp [4:0] $end
$var reg 3 E DMCtrl [2:0] $end
$var reg 1 . DMWr $end
$var reg 3 F ImmSrc [2:0] $end
$var reg 2 G RUDATAWrSrc [1:0] $end
$var reg 1 ' RUWr $end
$upscope $end
$scope module data_memory $end
$var wire 32 H Address [31:0] $end
$var wire 3 I DMCtrl [2:0] $end
$var wire 1 . DMWr $end
$var wire 32 J DataWr [31:0] $end
$var reg 32 K DataRd [31:0] $end
$scope begin $ivl_for_loop0 $end
$var integer 32 L i [31:0] $end
$upscope $end
$upscope $end
$scope module imm_gen $end
$var wire 3 M ImmSrc [2:0] $end
$var wire 25 N Inst [24:0] $end
$var reg 32 O ImmExt [31:0] $end
$upscope $end
$scope module instruction_memory $end
$var wire 32 P instruction [31:0] $end
$var wire 32 Q address [31:0] $end
$upscope $end
$scope module programm_counter $end
$var wire 32 R PC_Input [31:0] $end
$var wire 1 " clk $end
$var reg 32 S PC_Output [31:0] $end
$upscope $end
$scope module register_unit $end
$var wire 32 T RUDataWr [31:0] $end
$var wire 1 ' RUWr $end
$var wire 32 U RUrs1 [31:0] $end
$var wire 32 V RUrs2 [31:0] $end
$var wire 1 " clk $end
$var wire 5 W rd [4:0] $end
$var wire 5 X rs1 [4:0] $end
$var wire 5 Y rs2 [4:0] $end
$scope begin $ivl_for_loop1 $end
$var integer 32 Z i [31:0] $end
$upscope $end
$upscope $end
$upscope $end
$upscope $end
$enddefinitions $end
$comment Show the parameter values. $end
$dumpall
$end
#0
$dumpvars
b100000 Z
b10 Y
b0 X
b1010 W
b1111101000 V
b0 U
b10 T
b0 S
b100 R
b0 Q
b1000000000010100010011 P
b10 O
b100000000001010 N
b0 M
b100000000000 L
b0 K
b1111101000 J
b0 I
b10 H
b0 G
b0 F
b0 E
b0 D
b0 C
b10011 B
b0 A
b0 @
b0 ?
b1111101000 >
b0 =
b10 <
b0 ;
b10 :
b0 9
b100 8
b100 7
b10 6
b0 5
04
13
b0 2
b10 1
b0 0
b0 /
0.
b0 -
b10 ,
b0 +
0*
b0 )
b0 (
1'
b0 &
b1111101000 %
b1000000000010100010011 $
b10 #
0"
b10 !
$end
#5
b100 T
b100 !
b100 #
b100 1
b100 <
b100 H
b100 6
b100 :
b1000 7
b1000 R
b100 ,
b100 O
b1011 W
b0 %
b0 >
b0 J
b0 V
b100 Y
b1000000000001011 N
b1000 8
b10000000000010110010011 $
b10000000000010110010011 P
b100 )
b100 Q
b100 S
1"
#10
0"
#15
b10000 !
b10000 #
b10000 1
b10000 <
b10000 H
1*
b1000 6
b1000 :
b1000 5
b1000 9
b10000 7
b10000 R
b1100 T
b110 +
b110 F
b110 M
b10 (
b10 G
b10000 0
b10000 =
b10000 D
14
b1000 ,
b1000 O
b1101111 B
b1 W
b1000 Y
b10000000000000001 N
b1100 8
b100000000000000011101111 $
b100000000000000011101111 P
b1000 )
b1000 Q
b1000 S
1"
#20
0"
#25
b10100 7
b10100 R
b1111010100 !
b1111010100 #
b1111010100 1
b1111010100 <
b1111010100 H
b11111111111111111111111111101100 6
b11111111111111111111111111101100 :
0*
b1111101000 5
b1111101000 9
b1111010100 T
b11111111111111111111111111101100 ,
b11111111111111111111111111101100 O
b0 +
b0 F
b0 M
b0 (
b0 G
b0 0
b0 =
b0 D
04
b10011 B
b10 W
b1100 Y
b1111101000 &
b1111101000 ?
b1111101000 U
b10 X
b1111111011000001000000010 N
b1111111 A
b10100 8
b11111110110000010000000100010011 $
b11111110110000010000000100010011 P
b10000 )
b10000 Q
b10000 S
1"
#30
0"
#35
b1111010100 5
b1111010100 9
b1111010100 !
b1111010100 #
b1111010100 1
b1111010100 <
b1111010100 H
b0 6
b0 :
b11000 7
b11000 R
b1111010100 &
b1111010100 ?
b1111010100 U
b11000 T
b0 ,
b0 O
b1 +
b1 F
b1 M
b10 (
b10 G
0'
b10 /
b10 E
b10 I
1.
b100011 B
b0 W
b10 @
b1000 Y
b10000001001000000 N
b0 A
b11000 8
b100000010010000000100011 $
b100000010010000000100011 P
b10100 )
b10100 Q
b10100 S
1"
#40
0"
#45
b1111011000 !
b1111011000 #
b1111011000 1
b1111011000 <
b1111011000 H
b100 6
b100 :
b11100 7
b11100 R
b11100 T
b100 ,
b100 O
b100 W
b1001 Y
b10010001001000100 N
b11100 8
b100100010010001000100011 $
b100100010010001000100011 P
b11000 )
b11000 Q
b11000 S
1"
#50
0"
#55
b1111011100 !
b1111011100 #
b1111011100 1
b1111011100 <
b1111011100 H
b1000 6
b1000 :
b100000 7
b100000 R
b100000 T
b1000 ,
b1000 O
b1000 W
b10010 Y
b100100001001001000 N
b100000 8
b1001000010010010000100011 $
b1001000010010010000100011 P
b11100 )
b11100 Q
b11100 S
1"
#60
0"
#65
b1111100000 !
b1111100000 #
b1111100000 1
b1111100000 <
b1111100000 H
b1100 6
b1100 :
b100100 7
b100100 R
b100100 T
b1100 ,
b1100 O
b1100 W
b10011 Y
b100110001001001100 N
b100100 8
b1001100010010011000100011 $
b1001100010010011000100011 P
b100000 )
b100000 Q
b100000 S
1"
#70
0"
#75
b1111100100 !
b1111100100 #
b1111100100 1
b1111100100 <
b1111100100 H
b10000 6
b10000 :
b101000 7
b101000 R
b101000 T
b10000 ,
b10000 O
b10000 W
b1100 %
b1100 >
b1100 J
b1100 V
b1 Y
b10001001010000 N
b101000 8
b100010010100000100011 $
b100010010100000100011 P
b100100 )
b100100 Q
b100100 S
1"
#77
b1100 -
b1100 K
#80
0"
#85
b10 !
b10 #
b10 1
b10 <
b10 H
b0 6
b0 :
b10 5
b10 9
b101100 7
b101100 R
b10 T
b0 +
b0 F
b0 M
b0 (
b0 G
1'
b0 /
b0 E
b0 I
0.
b0 ,
b0 O
b10011 B
b1000 W
b0 @
b0 %
b0 >
b0 J
b0 V
b0 Y
b10 &
b10 ?
b10 U
b1010 X
b101000001000 N
b101100 8
b1010000010000010011 $
b1010000010000010011 P
b101000 )
b101000 Q
b101000 S
1"
#86
b0 -
b0 K
#90
0"
#95
b100 T
b100 !
b100 #
b100 1
b100 <
b100 H
b100 5
b100 9
b110000 7
b110000 R
b1001 W
b100 &
b100 ?
b100 U
b1011 X
b101100001001 N
b110000 8
b1011000010010010011 $
b1011000010010010011 P
b101100 )
b101100 Q
b101100 S
1"
#100
0"
#105
b1 T
b1 !
b1 #
b1 1
b1 <
b1 H
b1 6
b1 :
b0 5
b0 9
b110100 7
b110100 R
b1 ,
b1 O
b10010 W
b1100 %
b1100 >
b1100 J
b1100 V
b1 Y
b0 &
b0 ?
b0 U
b0 X
b10000000010010 N
b110100 8
b100000000100100010011 $
b100000000100100010011 P
b110000 )
b110000 Q
b110000 S
1"
#110
0"
#115
b0 T
b0 !
b0 #
b0 1
b0 <
b0 H
b0 6
b0 :
b111000 7
b111000 R
b0 ,
b0 O
b10011 W
b0 %
b0 >
b0 J
b0 V
b0 Y
b10011 N
b111000 8
b100110010011 $
b100110010011 P
b110100 )
b110100 Q
b110100 S
1"
#120
0"
#125
b1010100 !
b1010100 #
b1010100 1
b1010100 <
b1010100 H
b111000 5
b111000 9
b11100 6
b11100 :
b111100 7
b111100 R
b111100 T
b101 +
b101 F
b101 M
b10 (
b10 G
0'
b1101 0
b1101 =
b1101 D
14
b11100 ,
b11100 O
b1100011 B
b11100 W
b101 @
b100 %
b100 >
b100 J
b100 V
b1001 Y
b10011 X
b10011001110111100 N
b111100 8
b100110011101111001100011 $
b100110011101111001100011 P
b111000 )
b111000 Q
b111000 S
1"
#130
0"
#135
b1 !
b1 #
b1 1
b1 <
b1 H
b0 6
b0 :
0*
b1 5
b1 9
b1000000 7
b1000000 R
b1 T
b0 +
b0 F
b0 M
b0 (
b0 G
1'
b0 0
b0 =
b0 D
04
b0 ,
b0 O
b10011 B
b1010 W
b1 &
b1 ?
b1 U
b10010 X
b0 @
b0 %
b0 >
b0 J
b0 V
b0 Y
b1001000001010 N
b1000000 8
b10010000010100010011 $
b10010000010100010011 P
b111100 )
b111100 Q
b111100 S
1"
#140
0"
#145
b10 T
b10 !
b10 #
b10 1
b10 <
b10 H
b10 5
b10 9
b1000100 7
b1000100 R
b1011 W
b10 &
b10 ?
b10 U
b1000 X
b100000001011 N
b1000100 8
b1000000010110010011 $
b1000000010110010011 P
b1000000 )
b1000000 Q
b1000000 S
1"
#150
0"
#155
b1110100 !
b1110100 #
b1110100 1
b1110100 <
b1110100 H
b110000 6
b110000 :
b1000100 5
b1000100 9
1*
b1110100 7
b1110100 R
b1001000 T
b110000 ,
b110000 O
b110 +
b110 F
b110 M
b10 (
b10 G
b10000 0
b10000 =
b10000 D
14
b1101111 B
b1 W
b0 &
b0 ?
b0 U
b0 X
b10000 Y
b1100000000000000001 N
b1 A
b1001000 8
b11000000000000000011101111 $
b11000000000000000011101111 P
b1000100 )
b1000100 Q
b1000100 S
1"
#160
0"
#165
b1111000 7
b1111000 R
b1111000100 !
b1111000100 #
b1111000100 1
b1111000100 <
b1111000100 H
b11111111111111111111111111110000 6
b11111111111111111111111111110000 :
0*
b1111010100 5
b1111010100 9
b1111000100 T
b11111111111111111111111111110000 ,
b11111111111111111111111111110000 O
b0 +
b0 F
b0 M
b0 (
b0 G
b0 0
b0 =
b0 D
04
b10011 B
b10 W
b1111010100 &
b1111010100 ?
b1111010100 U
b10 X
b1111111100000001000000010 N
b1111111 A
b1111000 8
b11111111000000010000000100010011 $
b11111111000000010000000100010011 P
b1110100 )
b1110100 Q
b1110100 S
1"
#170
0"
#175
b1111000100 5
b1111000100 9
b1111000100 !
b1111000100 #
b1111000100 1
b1111000100 <
b1111000100 H
b0 6
b0 :
b1111100 7
b1111100 R
b1111000100 &
b1111000100 ?
b1111000100 U
b1111100 T
b0 ,
b0 O
b1 +
b1 F
b1 M
b10 (
b10 G
0'
b10 /
b10 E
b10 I
1.
b100011 B
b0 W
b10 @
b10 %
b10 >
b10 J
b10 V
b1000 Y
b10000001001000000 N
b0 A
b1111100 8
b100000010010000000100011 $
b100000010010000000100011 P
b1111000 )
b1111000 Q
b1111000 S
1"
#177
b10 -
b10 K
#180
0"
#185
b1111001000 !
b1111001000 #
b1111001000 1
b1111001000 <
b1111001000 H
b100 6
b100 :
b10000000 7
b10000000 R
b10000000 T
b100 ,
b100 O
b100 W
b100 %
b100 >
b100 J
b100 V
b1001 Y
b10010001001000100 N
b10000000 8
b100100010010001000100011 $
b100100010010001000100011 P
b1111100 )
b1111100 Q
b1111100 S
1"
#186
b0 -
b0 K
#187
b100 -
b100 K
#190
0"
#195
b1111001100 !
b1111001100 #
b1111001100 1
b1111001100 <
b1111001100 H
b1000 6
b1000 :
b10000100 7
b10000100 R
b10000100 T
b1000 ,
b1000 O
b1000 W
b1 %
b1 >
b1 J
b1 V
b10010 Y
b100100001001001000 N
b10000100 8
b1001000010010010000100011 $
b1001000010010010000100011 P
b10000000 )
b10000000 Q
b10000000 S
1"
#196
b0 -
b0 K
#197
b1 -
b1 K
#200
0"
#205
b1111010000 !
b1111010000 #
b1111010000 1
b1111010000 <
b1111010000 H
b1100 6
b1100 :
b10001000 7
b10001000 R
b10001000 T
b1100 ,
b1100 O
b1100 W
b0 %
b0 >
b0 J
b0 V
b10011 Y
b100110001001001100 N
b10001000 8
b1001100010010011000100011 $
b1001100010010011000100011 P
b10000100 )
b10000100 Q
b10000100 S
1"
#206
b0 -
b0 K
#210
0"
#215
b1 !
b1 #
b1 1
b1 <
b1 H
b0 6
b0 :
b1 5
b1 9
b10001100 7
b10001100 R
b1 T
b0 +
b0 F
b0 M
b0 (
b0 G
1'
b0 /
b0 E
b0 I
0.
b0 ,
b0 O
b10011 B
b1000 W
b0 @
b1 &
b1 ?
b1 U
b1010 X
b0 Y
b101000001000 N
b10001100 8
b1010000010000010011 $
b1010000010000010011 P
b10001000 )
b10001000 Q
b10001000 S
1"
#220
0"
#225
b10 T
b10 !
b10 #
b10 1
b10 <
b10 H
b10 5
b10 9
b10010000 7
b10010000 R
b1001 W
b10 &
b10 ?
b10 U
b1011 X
b101100001001 N
b10010000 8
b1011000010010010011 $
b1011000010010010011 P
b10001100 )
b10001100 Q
b10001100 S
1"
#230
0"
#235
b0 T
b0 !
b0 #
b0 1
b0 <
b0 H
b0 5
b0 9
b10010100 7
b10010100 R
b10010 W
b0 &
b0 ?
b0 U
b0 X
b10010 N
b10010100 8
b100100010011 $
b100100010011 P
b10010000 )
b10010000 Q
b10010000 S
1"
#240
0"
#245
b10011000 7
b10011000 R
b10011 W
b10011 N
b10011000 8
b100110010011 $
b100110010011 P
b10010100 )
b10010100 Q
b10010100 S
1"
#250
0"
#255
b10101000 !
b10101000 #
b10101000 1
b10101000 <
b10101000 H
b10011000 5
b10011000 9
b10000 6
b10000 :
b10011100 7
b10011100 R
b10011100 T
b101 +
b101 F
b101 M
b10 (
b10 G
0'
b1101 0
b1101 =
b1101 D
14
b10000 ,
b10000 O
b1100011 B
b10000 W
b101 @
b10 %
b10 >
b10 J
b10 V
b1001 Y
b10011 X
b10011001110110000 N
b10011100 8
b100110011101100001100011 $
b100110011101100001100011 P
b10011000 )
b10011000 Q
b10011000 S
1"
#260
0"
#265
b1 !
b1 #
b1 1
b1 <
b1 H
b1 6
b1 :
b0 5
b0 9
b10100000 7
b10100000 R
b1 T
b0 +
b0 F
b0 M
b0 (
b0 G
1'
b0 0
b0 =
b0 D
03
04
b1000 ,
b1000 O
b110011 B
b10010 W
b10010 X
b0 @
b1 %
b1 >
b1 J
b1 V
b1000 Y
b10001001000010010 N
b10100000 8
b100010010000100100110011 $
b100010010000100100110011 P
b10011100 )
b10011100 Q
b10011100 S
1"
#270
0"
#275
b1 6
b1 :
b10100100 7
b10100100 R
13
b1 ,
b1 O
b10011 W
b10011 B
b10011 X
b1001000 %
b1001000 >
b1001000 J
b1001000 V
b1 Y
b11001100010011 N
b10100100 8
b110011000100110010011 $
b110011000100110010011 P
b10100000 )
b10100000 Q
b10100000 S
1"
#280
0"
#285
b10011000 !
b10011000 #
b10011000 1
b10011000 <
b10011000 H
b11111111111111111111111111110100 6
b11111111111111111111111111110100 :
b10100100 5
b10100100 9
1*
b10011000 7
b10011000 R
b10101000 T
b11111111111111111111111111110100 ,
b11111111111111111111111111110100 O
b101 +
b101 F
b101 M
b10 (
b10 G
0'
b1101 0
b1101 =
b1101 D
14
b1100011 B
b10101 W
b101 @
b0 %
b0 >
b0 J
b0 V
b0 Y
b0 X
b1111111000000000010110101 N
b1111111 A
b10101000 8
b11111110000000000101101011100011 $
b11111110000000000101101011100011 P
b10100100 )
b10100100 Q
b10100100 S
1"
#290
0"
#295
b10011100 7
b10011100 R
b10101000 !
b10101000 #
b10101000 1
b10101000 <
b10101000 H
b10000 6
b10000 :
0*
b10011000 5
b10011000 9
b10011100 T
b10000 ,
b10000 O
b10000 W
b10 %
b10 >
b10 J
b10 V
b1001 Y
b1 &
b1 ?
b1 U
b10011 X
b10011001110110000 N
b0 A
b10011100 8
b100110011101100001100011 $
b100110011101100001100011 P
b10011000 )
b10011000 Q
b10011000 S
1"
#300
0"
#305
b10 !
b10 #
b10 1
b10 <
b10 H
b1 6
b1 :
0*
b1 5
b1 9
b10100000 7
b10100000 R
b10 T
b0 +
b0 F
b0 M
b0 (
b0 G
1'
b0 0
b0 =
b0 D
03
04
b1000 ,
b1000 O
b110011 B
b10010 W
b10010 X
b0 @
b1 %
b1 >
b1 J
b1 V
b1000 Y
b10001001000010010 N
b10100000 8
b100010010000100100110011 $
b100010010000100100110011 P
b10011100 )
b10011100 Q
b10011100 S
1"
#310
0"
#315
b1 6
b1 :
b10100100 7
b10100100 R
13
b1 ,
b1 O
b10011 W
b10011 B
b10011 X
b1001000 %
b1001000 >
b1001000 J
b1001000 V
b1 Y
b11001100010011 N
b10100100 8
b110011000100110010011 $
b110011000100110010011 P
b10100000 )
b10100000 Q
b10100000 S
1"
#320
0"
