VGA/Screen_RAM.sv
module Screen_RAM (
    input logic clk,
    input logic [7:0] scrX,
    input logic [6:0] scrY,
    input logic selector,
    output logic [7:0] caracter
);
    logic [7:0] message [0:10239];
    logic [14:0] address;

    initial begin
        address = 15'b0;
        for (int i = 0; i < 10239; i++) begin
            message[i] = 8'b0;
        end
        $readmemh("Screen_test.txt", message);
    end

    always @(posedge clk) begin
        address <= {scrY, scrX};

        if (~selector) begin
            caracter <= 8'b0; //NULL
        end else if (address > 15'd10239) begin
            caracter <= 8'b0;
        end else begin
            caracter <= message[address];
        end
    end
endmodule

Testbenches/Testbench_ScreenRAM.sv
module tb_ScreenRAM;
    logic clk;
    logic [7:0] scrX;
    logic [6:0] scrY;
    logic selector;
    logic [7:0] caracter;

    Screen_RAM Screen_RAM_Test(
        .clk(clk),
        .scrX(scrX),
        .scrY(scrY),
        .selector(selector),
        .caracter(caracter)
    );
    
    initial
    begin
        clk = 1'b0;
        scrX = 8'b0;
        scrY = 7'b0;
        selector = 1'b1;

        $dumpfile("dump.vcd");
        $dumpvars;

        #500;
        $finish;
    end

    always begin
        #1 clk = ~clk;
    end

    always @(posedge clk) begin
        if (scrX <= 8'd159) begin
            scrX = scrX + 1;
        end else begin
            scrX = 8'b0;
            scrY = scrY + 1;
        end
        #1
        $display("caracter = %h", caracter);
    end
endmodule

dump.vcd
$date
	Sat May 25 16:09:11 2024
$end
$version
	Icarus Verilog
$end
$timescale
	1s
$end
$scope module tb_ScreenRAM $end
$var wire 8 ! caracter [7:0] $end
$var reg 1 " clk $end
$var reg 8 # scrX [7:0] $end
$var reg 7 $ scrY [6:0] $end
$var reg 1 % selector $end
$scope module Screen_RAM_Test $end
$var wire 1 " clk $end
$var wire 8 & scrX [7:0] $end
$var wire 7 ' scrY [6:0] $end
$var wire 1 % selector $end
$var reg 15 ( address [14:0] $end
$var reg 8 ) caracter [7:0] $end
$scope begin $ivl_for_loop0 $end
$var integer 32 * i [31:0] $end
$upscope $end
$upscope $end
$upscope $end
$enddefinitions $end
$comment Show the parameter values. $end
$dumpall
$end
#0
$dumpvars
b10011111111111 *
bx )
b0 (
b0 '
b0 &
1%
b0 $
b0 #
0"
bx !
$end
#1
b1001000 !
b1001000 )
b1 (
b1 #
b1 &
1"
#2
0"
#3
b1101111 !
b1101111 )
b10 (
b10 #
b10 &
1"
#4
0"
#5
b1101100 !
b1101100 )
b11 (
b11 #
b11 &
1"
#6
0"
#7
b1100001 !
b1100001 )
b100 (
b100 #
b100 &
1"
#8
0"
#9
b100000 !
b100000 )
b101 (
b101 #
b101 &
1"
#10
0"
#11
b1101101 !
b1101101 )
b110 (
b110 #
b110 &
1"
#12
0"
#13
b1110101 !
b1110101 )
b111 (
b111 #
b111 &
1"
#14
0"
#15
b1101110 !
b1101110 )
b1000 (
b1000 #
b1000 &
1"
#16
0"
#17
b1100100 !
b1100100 )
b1001 (
b1001 #
b1001 &
1"
#18
0"
#19
b1101111 !
b1101111 )
b1010 (
b1010 #
b1010 &
1"
#20
0"
#21
b0 !
b0 )
b1011 (
b1011 #
b1011 &
1"
#22
0"
#23
b1100 (
b1100 #
b1100 &
1"
#24
0"
#25
b1101 (
b1101 #
b1101 &
1"
#26
0"
#27
b1110 (
b1110 #
b1110 &
1"
#28
0"
#29
b1111 (
b1111 #
b1111 &
1"
#30
0"
#31
b10000 (
b10000 #
b10000 &
1"
#32
0"
#33
b10001 (
b10001 #
b10001 &
1"
#34
0"
#35
b10010 (
b10010 #
b10010 &
1"
#36
0"
#37
b10011 (
b10011 #
b10011 &
1"
#38
0"
#39
b10100 (
b10100 #
b10100 &
1"
#40
0"
#41
b10101 (
b10101 #
b10101 &
1"
#42
0"
#43
b10110 (
b10110 #
b10110 &
1"
#44
0"
#45
b10111 (
b10111 #
b10111 &
1"
#46
0"
#47
b11000 (
b11000 #
b11000 &
1"
#48
0"
#49
b11001 (
b11001 #
b11001 &
1"
#50
0"
#51
b11010 (
b11010 #
b11010 &
1"
#52
0"
#53
b11011 (
b11011 #
b11011 &
1"
#54
0"
#55
b11100 (
b11100 #
b11100 &
1"
#56
0"
#57
b11101 (
b11101 #
b11101 &
1"
#58
0"
#59
b11110 (
b11110 #
b11110 &
1"
#60
0"
#61
b11111 (
b11111 #
b11111 &
1"
#62
0"
#63
b100000 (
b100000 #
b100000 &
1"
#64
0"
#65
b100001 (
b100001 #
b100001 &
1"
#66
0"
#67
b100010 (
b100010 #
b100010 &
1"
#68
0"
#69
b100011 (
b100011 #
b100011 &
1"
#70
0"
#71
b100100 (
b100100 #
b100100 &
1"
#72
0"
#73
b100101 (
b100101 #
b100101 &
1"
#74
0"
#75
b100110 (
b100110 #
b100110 &
1"
#76
0"
#77
b100111 (
b100111 #
b100111 &
1"
#78
0"
#79
b101000 (
b101000 #
b101000 &
1"
#80
0"
#81
b101001 (
b101001 #
b101001 &
1"
#82
0"
#83
b101010 (
b101010 #
b101010 &
1"
#84
0"
#85
b101011 (
b101011 #
b101011 &
1"
#86
0"
#87
b101100 (
b101100 #
b101100 &
1"
#88
0"
#89
b101101 (
b101101 #
b101101 &
1"
#90
0"
#91
b101110 (
b101110 #
b101110 &
1"
#92
0"
#93
b101111 (
b101111 #
b101111 &
1"
#94
0"
#95
b110000 (
b110000 #
b110000 &
1"
#96
0"
#97
b110001 (
b110001 #
b110001 &
1"
#98
0"
#99
b110010 (
b110010 #
b110010 &
1"
#100
0"
#101
b110011 (
b110011 #
b110011 &
1"
#102
0"
#103
b110100 (
b110100 #
b110100 &
1"
#104
0"
#105
b110101 (
b110101 #
b110101 &
1"
#106
0"
#107
b110110 (
b110110 #
b110110 &
1"
#108
0"
#109
b110111 (
b110111 #
b110111 &
1"
#110
0"
#111
b111000 (
b111000 #
b111000 &
1"
#112
0"
#113
b111001 (
b111001 #
b111001 &
1"
#114
0"
#115
b111010 (
b111010 #
b111010 &
1"
#116
0"
#117
b111011 (
b111011 #
b111011 &
1"
#118
0"
#119
b111100 (
b111100 #
b111100 &
1"
#120
0"
#121
b111101 (
b111101 #
b111101 &
1"
#122
0"
#123
b111110 (
b111110 #
b111110 &
1"
#124
0"
#125
b111111 (
b111111 #
b111111 &
1"
#126
0"
#127
b1000000 (
b1000000 #
b1000000 &
1"
#128
0"
#129
b1000001 (
b1000001 #
b1000001 &
1"
#130
0"
#131
b1000010 (
b1000010 #
b1000010 &
1"
#132
0"
#133
b1000011 (
b1000011 #
b1000011 &
1"
#134
0"
#135
b1000100 (
b1000100 #
b1000100 &
1"
#136
0"
#137
b1000101 (
b1000101 #
b1000101 &
1"
#138
0"
#139
b1000110 (
b1000110 #
b1000110 &
1"
#140
0"
#141
b1000111 (
b1000111 #
b1000111 &
1"
#142
0"
#143
b1001000 (
b1001000 #
b1001000 &
1"
#144
0"
#145
b1001001 (
b1001001 #
b1001001 &
1"
#146
0"
#147
b1001010 (
b1001010 #
b1001010 &
1"
#148
0"
#149
b1001011 (
b1001011 #
b1001011 &
1"
#150
0"
#151
b1001100 (
b1001100 #
b1001100 &
1"
#152
0"
#153
b1001101 (
b1001101 #
b1001101 &
1"
#154
0"
#155
b1001110 (
b1001110 #
b1001110 &
1"
#156
0"
#157
b1001111 (
b1001111 #
b1001111 &
1"
#158
0"
#159
b1010000 (
b1010000 #
b1010000 &
1"
#160
0"
#161
b1010001 (
b1010001 #
b1010001 &
1"
#162
0"
#163
b1010010 (
b1010010 #
b1010010 &
1"
#164
0"
#165
b1010011 (
b1010011 #
b1010011 &
1"
#166
0"
#167
b1010100 (
b1010100 #
b1010100 &
1"
#168
0"
#169
b1010101 (
b1010101 #
b1010101 &
1"
#170
0"
#171
b1010110 (
b1010110 #
b1010110 &
1"
#172
0"
#173
b1010111 (
b1010111 #
b1010111 &
1"
#174
0"
#175
b1011000 (
b1011000 #
b1011000 &
1"
#176
0"
#177
b1011001 (
b1011001 #
b1011001 &
1"
#178
0"
#179
b1011010 (
b1011010 #
b1011010 &
1"
#180
0"
#181
b1011011 (
b1011011 #
b1011011 &
1"
#182
0"
#183
b1011100 (
b1011100 #
b1011100 &
1"
#184
0"
#185
b1011101 (
b1011101 #
b1011101 &
1"
#186
0"
#187
b1011110 (
b1011110 #
b1011110 &
1"
#188
0"
#189
b1011111 (
b1011111 #
b1011111 &
1"
#190
0"
#191
b1100000 (
b1100000 #
b1100000 &
1"
#192
0"
#193
b1100001 (
b1100001 #
b1100001 &
1"
#194
0"
#195
b1100010 (
b1100010 #
b1100010 &
1"
#196
0"
#197
b1100011 (
b1100011 #
b1100011 &
1"
#198
0"
#199
b1100100 (
b1100100 #
b1100100 &
1"
#200
0"
#201
b1100101 (
b1100101 #
b1100101 &
1"
#202
0"
#203
b1100110 (
b1100110 #
b1100110 &
1"
#204
0"
#205
b1100111 (
b1100111 #
b1100111 &
1"
#206
0"
#207
b1101000 (
b1101000 #
b1101000 &
1"
#208
0"
#209
b1101001 (
b1101001 #
b1101001 &
1"
#210
0"
#211
b1101010 (
b1101010 #
b1101010 &
1"
#212
0"
#213
b1101011 (
b1101011 #
b1101011 &
1"
#214
0"
#215
b1101100 (
b1101100 #
b1101100 &
1"
#216
0"
#217
b1101101 (
b1101101 #
b1101101 &
1"
#218
0"
#219
b1101110 (
b1101110 #
b1101110 &
1"
#220
0"
#221
b1101111 (
b1101111 #
b1101111 &
1"
#222
0"
#223
b1110000 (
b1110000 #
b1110000 &
1"
#224
0"
#225
b1110001 (
b1110001 #
b1110001 &
1"
#226
0"
#227
b1110010 (
b1110010 #
b1110010 &
1"
#228
0"
#229
b1110011 (
b1110011 #
b1110011 &
1"
#230
0"
#231
b1110100 (
b1110100 #
b1110100 &
1"
#232
0"
#233
b1110101 (
b1110101 #
b1110101 &
1"
#234
0"
#235
b1110110 (
b1110110 #
b1110110 &
1"
#236
0"
#237
b1110111 (
b1110111 #
b1110111 &
1"
#238
0"
#239
b1111000 (
b1111000 #
b1111000 &
1"
#240
0"
#241
b1111001 (
b1111001 #
b1111001 &
1"
#242
0"
#243
b1111010 (
b1111010 #
b1111010 &
1"
#244
0"
#245
b1111011 (
b1111011 #
b1111011 &
1"
#246
0"
#247
b1111100 (
b1111100 #
b1111100 &
1"
#248
0"
#249
b1111101 (
b1111101 #
b1111101 &
1"
#250
0"
#251
b1111110 (
b1111110 #
b1111110 &
1"
#252
0"
#253
b1111111 (
b1111111 #
b1111111 &
1"
#254
0"
#255
b10000000 (
b10000000 #
b10000000 &
1"
#256
0"
#257
b10000001 (
b10000001 #
b10000001 &
1"
#258
0"
#259
b10000010 (
b10000010 #
b10000010 &
1"
#260
0"
#261
b10000011 (
b10000011 #
b10000011 &
1"
#262
0"
#263
b10000100 (
b10000100 #
b10000100 &
1"
#264
0"
#265
b10000101 (
b10000101 #
b10000101 &
1"
#266
0"
#267
b10000110 (
b10000110 #
b10000110 &
1"
#268
0"
#269
b10000111 (
b10000111 #
b10000111 &
1"
#270
0"
#271
b10001000 (
b10001000 #
b10001000 &
1"
#272
0"
#273
b10001001 (
b10001001 #
b10001001 &
1"
#274
0"
#275
b10001010 (
b10001010 #
b10001010 &
1"
#276
0"
#277
b10001011 (
b10001011 #
b10001011 &
1"
#278
0"
#279
b10001100 (
b10001100 #
b10001100 &
1"
#280
0"
#281
b10001101 (
b10001101 #
b10001101 &
1"
#282
0"
#283
b10001110 (
b10001110 #
b10001110 &
1"
#284
0"
#285
b10001111 (
b10001111 #
b10001111 &
1"
#286
0"
#287
b10010000 (
b10010000 #
b10010000 &
1"
#288
0"
#289
b10010001 (
b10010001 #
b10010001 &
1"
#290
0"
#291
b10010010 (
b10010010 #
b10010010 &
1"
#292
0"
#293
b10010011 (
b10010011 #
b10010011 &
1"
#294
0"
#295
b10010100 (
b10010100 #
b10010100 &
1"
#296
0"
#297
b10010101 (
b10010101 #
b10010101 &
1"
#298
0"
#299
b10010110 (
b10010110 #
b10010110 &
1"
#300
0"
#301
b10010111 (
b10010111 #
b10010111 &
1"
#302
0"
#303
b10011000 (
b10011000 #
b10011000 &
1"
#304
0"
#305
b10011001 (
b10011001 #
b10011001 &
1"
#306
0"
#307
b10011010 (
b10011010 #
b10011010 &
1"
#308
0"
#309
b10011011 (
b10011011 #
b10011011 &
1"
#310
0"
#311
b10011100 (
b10011100 #
b10011100 &
1"
#312
0"
#313
b10011101 (
b10011101 #
b10011101 &
1"
#314
0"
#315
b10011110 (
b10011110 #
b10011110 &
1"
#316
0"
#317
b10011111 (
b10011111 #
b10011111 &
1"
#318
0"
#319
b10100000 (
b10100000 #
b10100000 &
1"
#320
0"
#321
b100000000 (
b1 $
b1 '
b0 #
b0 &
1"
#322
0"
#323
b100000001 (
b1 #
b1 &
1"
#324
0"
#325
b100000010 (
b10 #
b10 &
1"
#326
0"
#327
b100000011 (
b11 #
b11 &
1"
#328
0"
#329
b100000100 (
b100 #
b100 &
1"
#330
0"
#331
b100000101 (
b101 #
b101 &
1"
#332
0"
#333
b100000110 (
b110 #
b110 &
1"
#334
0"
#335
b100000111 (
b111 #
b111 &
1"
#336
0"
#337
b100001000 (
b1000 #
b1000 &
1"
#338
0"
#339
b100001001 (
b1001 #
b1001 &
1"
#340
0"
#341
b100001010 (
b1010 #
b1010 &
1"
#342
0"
#343
b100001011 (
b1011 #
b1011 &
1"
#344
0"
#345
b100001100 (
b1100 #
b1100 &
1"
#346
0"
#347
b100001101 (
b1101 #
b1101 &
1"
#348
0"
#349
b100001110 (
b1110 #
b1110 &
1"
#350
0"
#351
b100001111 (
b1111 #
b1111 &
1"
#352
0"
#353
b100010000 (
b10000 #
b10000 &
1"
#354
0"
#355
b100010001 (
b10001 #
b10001 &
1"
#356
0"
#357
b100010010 (
b10010 #
b10010 &
1"
#358
0"
#359
b100010011 (
b10011 #
b10011 &
1"
#360
0"
#361
b100010100 (
b10100 #
b10100 &
1"
#362
0"
#363
b100010101 (
b10101 #
b10101 &
1"
#364
0"
#365
b100010110 (
b10110 #
b10110 &
1"
#366
0"
#367
b100010111 (
b10111 #
b10111 &
1"
#368
0"
#369
b100011000 (
b11000 #
b11000 &
1"
#370
0"
#371
b100011001 (
b11001 #
b11001 &
1"
#372
0"
#373
b100011010 (
b11010 #
b11010 &
1"
#374
0"
#375
b100011011 (
b11011 #
b11011 &
1"
#376
0"
#377
b100011100 (
b11100 #
b11100 &
1"
#378
0"
#379
b100011101 (
b11101 #
b11101 &
1"
#380
0"
#381
b100011110 (
b11110 #
b11110 &
1"
#382
0"
#383
b100011111 (
b11111 #
b11111 &
1"
#384
0"
#385
b100100000 (
b100000 #
b100000 &
1"
#386
0"
#387
b100100001 (
b100001 #
b100001 &
1"
#388
0"
#389
b100100010 (
b100010 #
b100010 &
1"
#390
0"
#391
b100100011 (
b100011 #
b100011 &
1"
#392
0"
#393
b100100100 (
b100100 #
b100100 &
1"
#394
0"
#395
b100100101 (
b100101 #
b100101 &
1"
#396
0"
#397
b100100110 (
b100110 #
b100110 &
1"
#398
0"
#399
b100100111 (
b100111 #
b100111 &
1"
#400
0"
#401
b100101000 (
b101000 #
b101000 &
1"
#402
0"
#403
b100101001 (
b101001 #
b101001 &
1"
#404
0"
#405
b100101010 (
b101010 #
b101010 &
1"
#406
0"
#407
b100101011 (
b101011 #
b101011 &
1"
#408
0"
#409
b100101100 (
b101100 #
b101100 &
1"
#410
0"
#411
b100101101 (
b101101 #
b101101 &
1"
#412
0"
#413
b100101110 (
b101110 #
b101110 &
1"
#414
0"
#415
b100101111 (
b101111 #
b101111 &
1"
#416
0"
#417
b100110000 (
b110000 #
b110000 &
1"
#418
0"
#419
b100110001 (
b110001 #
b110001 &
1"
#420
0"
#421
b100110010 (
b110010 #
b110010 &
1"
#422
0"
#423
b100110011 (
b110011 #
b110011 &
1"
#424
0"
#425
b100110100 (
b110100 #
b110100 &
1"
#426
0"
#427
b100110101 (
b110101 #
b110101 &
1"
#428
0"
#429
b100110110 (
b110110 #
b110110 &
1"
#430
0"
#431
b100110111 (
b110111 #
b110111 &
1"
#432
0"
#433
b100111000 (
b111000 #
b111000 &
1"
#434
0"
#435
b100111001 (
b111001 #
b111001 &
1"
#436
0"
#437
b100111010 (
b111010 #
b111010 &
1"
#438
0"
#439
b100111011 (
b111011 #
b111011 &
1"
#440
0"
#441
b100111100 (
b111100 #
b111100 &
1"
#442
0"
#443
b100111101 (
b111101 #
b111101 &
1"
#444
0"
#445
b100111110 (
b111110 #
b111110 &
1"
#446
0"
#447
b100111111 (
b111111 #
b111111 &
1"
#448
0"
#449
b101000000 (
b1000000 #
b1000000 &
1"
#450
0"
#451
b101000001 (
b1000001 #
b1000001 &
1"
#452
0"
#453
b101000010 (
b1000010 #
b1000010 &
1"
#454
0"
#455
b101000011 (
b1000011 #
b1000011 &
1"
#456
0"
#457
b101000100 (
b1000100 #
b1000100 &
1"
#458
0"
#459
b101000101 (
b1000101 #
b1000101 &
1"
#460
0"
#461
b101000110 (
b1000110 #
b1000110 &
1"
#462
0"
#463
b101000111 (
b1000111 #
b1000111 &
1"
#464
0"
#465
b101001000 (
b1001000 #
b1001000 &
1"
#466
0"
#467
b101001001 (
b1001001 #
b1001001 &
1"
#468
0"
#469
b101001010 (
b1001010 #
b1001010 &
1"
#470
0"
#471
b101001011 (
b1001011 #
b1001011 &
1"
#472
0"
#473
b101001100 (
b1001100 #
b1001100 &
1"
#474
0"
#475
b101001101 (
b1001101 #
b1001101 &
1"
#476
0"
#477
b101001110 (
b1001110 #
b1001110 &
1"
#478
0"
#479
b101001111 (
b1001111 #
b1001111 &
1"
#480
0"
#481
b101010000 (
b1010000 #
b1010000 &
1"
#482
0"
#483
b101010001 (
b1010001 #
b1010001 &
1"
#484
0"
#485
b101010010 (
b1010010 #
b1010010 &
1"
#486
0"
#487
b101010011 (
b1010011 #
b1010011 &
1"
#488
0"
#489
b101010100 (
b1010100 #
b1010100 &
1"
#490
0"
#491
b101010101 (
b1010101 #
b1010101 &
1"
#492
0"
#493
b101010110 (
b1010110 #
b1010110 &
1"
#494
0"
#495
b101010111 (
b1010111 #
b1010111 &
1"
#496
0"
#497
b101011000 (
b1011000 #
b1011000 &
1"
#498
0"
#499
b101011001 (
b1011001 #
b1011001 &
1"
